vizic/__init__.py
vizic/_version.py
vizic/astroleaflet.py
vizic/connection.py
vizic/control_widgets.py
vizic/leaflet.py
vizic/utils.py
vizic/mongo_ext/__init__.py
vizic/mongo_ext/db_connect.py
vizic/mongo_ext/extension.py
vizic/static/2f19f5c5efabd77841f96226b50944c1.png
vizic/static/30360dc9bc1709ecf370230c6619e1cf.png
vizic/static/32ae3f598d1e4c685ba453ff323dc0bf.png
vizic/static/4296141752702dffcef4c5e327b47b39.png
vizic/static/69d89e51f62b6a582c311c35c0f778aa.svg
vizic/static/7d590d0c76f795c775896429a76c3c79.png
vizic/static/9bfe6912db7d03ae5ffe950039b162d5.png
vizic/static/d5c623469a876abe56664cf2fc552c3e.png
vizic/static/extension.js
vizic/static/fullscreen.png
vizic/static/fullscreen@2x.png
vizic/static/index.js
vizic/static/index.js.map
vizic/static/layers-2x.png
vizic/static/layers.png
vizic/static/marker-icon-2x.png
vizic/static/marker-icon.png
vizic/static/marker-shadow.png
vizic-0.3.data/data/share/jupyter/nbextensions/jupyter-vizic/2f19f5c5efabd77841f96226b50944c1.png
vizic-0.3.data/data/share/jupyter/nbextensions/jupyter-vizic/30360dc9bc1709ecf370230c6619e1cf.png
vizic-0.3.data/data/share/jupyter/nbextensions/jupyter-vizic/32ae3f598d1e4c685ba453ff323dc0bf.png
vizic-0.3.data/data/share/jupyter/nbextensions/jupyter-vizic/4296141752702dffcef4c5e327b47b39.png
vizic-0.3.data/data/share/jupyter/nbextensions/jupyter-vizic/7d590d0c76f795c775896429a76c3c79.png
vizic-0.3.data/data/share/jupyter/nbextensions/jupyter-vizic/9bfe6912db7d03ae5ffe950039b162d5.png
vizic-0.3.data/data/share/jupyter/nbextensions/jupyter-vizic/d5c623469a876abe56664cf2fc552c3e.png
vizic-0.3.data/data/share/jupyter/nbextensions/jupyter-vizic/extension.js
vizic-0.3.data/data/share/jupyter/nbextensions/jupyter-vizic/fullscreen.png
vizic-0.3.data/data/share/jupyter/nbextensions/jupyter-vizic/fullscreen@2x.png
vizic-0.3.data/data/share/jupyter/nbextensions/jupyter-vizic/index.js
vizic-0.3.data/data/share/jupyter/nbextensions/jupyter-vizic/index.js.map
vizic-0.3.dist-info/DESCRIPTION.rst
vizic-0.3.dist-info/METADATA
vizic-0.3.dist-info/RECORD
vizic-0.3.dist-info/WHEEL
vizic-0.3.dist-info/metadata.json
vizic-0.3.dist-info/top_level.txt
